[
  {
    "id": "phy_001",
    "npi": "1000000001",
    "firstName": "Aisha",
    "lastName": "Patel",
    "specialty": "Medical Oncology",
    "affiliation": "UCSF Medical Center",
    "city": "San Francisco",
    "state": "CA",
    "icd10ClaimVolume": {"C341": 87, "C342": 12, "C343": 6},
    "totalNSCLCClaims": 105,
    "volumeTier": "very_high",
    "email": "a.patel@ucsf.example",
    "boardCertified": true
  },
  {
    "id": "phy_002",
    "npi": "1000000002",
    "firstName": "Miguel",
    "lastName": "Chen",
    "specialty": "Medical Oncology",
    "affiliation": "Stanford Health Care",
    "city": "Palo Alto",
    "state": "CA",
    "icd10ClaimVolume": {"C341": 45, "C342": 31},
    "totalNSCLCClaims": 76,
    "volumeTier": "high",
    "email": "m.chen@stanford-oncology.example",
    "boardCertified": true
  },
  {
    "id": "phy_003",
    "npi": "1000000003",
    "firstName": "Elena",
    "lastName": "Rodriguez",
    "specialty": "Medical Oncology",
    "affiliation": "UCLA Health",
    "city": "Los Angeles",
    "state": "CA",
    "icd10ClaimVolume": {"C341": 64, "C342": 18, "C349": 7},
    "totalNSCLCClaims": 89,
    "volumeTier": "high",
    "email": "e.rodriguez@ucla-oncology.example",
    "boardCertified": true
  },
  {
    "id": "phy_004",
    "npi": "1000000004",
    "firstName": "Noah",
    "lastName": "Kim",
    "specialty": "Thoracic Surgery",
    "affiliation": "Cedars-Sinai Medical Center",
    "city": "Los Angeles",
    "state": "CA",
    "icd10ClaimVolume": {"C341": 29, "C342": 8},
    "totalNSCLCClaims": 37,
    "volumeTier": "low",
    "email": "n.kim@cedars.example",
    "boardCertified": true
  },
  {
    "id": "phy_005",
    "npi": "1000000005",
    "firstName": "Priya",
    "lastName": "Shah",
    "specialty": "Medical Oncology",
    "affiliation": "Memorial Sloan Kettering Cancer Center",
    "city": "New York",
    "state": "NY",
    "icd10ClaimVolume": {"C341": 112, "C342": 46, "C343": 20},
    "totalNSCLCClaims": 178,
    "volumeTier": "very_high",
    "email": "p.shah@msk.example",
    "boardCertified": true
  },
  {
    "id": "phy_006",
    "npi": "1000000006",
    "firstName": "David",
    "lastName": "Stein",
    "specialty": "Medical Oncology",
    "affiliation": "NYU Langone Health",
    "city": "New York",
    "state": "NY",
    "icd10ClaimVolume": {"C341": 72, "C342": 25, "C349": 5},
    "totalNSCLCClaims": 102,
    "volumeTier": "high",
    "email": "d.stein@nyulangone.example",
    "boardCertified": true
  },
  {
    "id": "phy_007",
    "npi": "1000000007",
    "firstName": "Mei",
    "lastName": "Lin",
    "specialty": "Medical Oncology",
    "affiliation": "Mount Sinai Hospital",
    "city": "New York",
    "state": "NY",
    "icd10ClaimVolume": {"C341": 50, "C342": 38},
    "totalNSCLCClaims": 88,
    "volumeTier": "high",
    "email": "m.lin@mountsinai-oncology.example",
    "boardCertified": true
  },
  {
    "id": "phy_008",
    "npi": "1000000008",
    "firstName": "Grace",
    "lastName": "Osei",
    "specialty": "Medical Oncology",
    "affiliation": "NewYork-Presbyterian",
    "city": "New York",
    "state": "NY",
    "icd10ClaimVolume": {"C341": 58, "C342": 24},
    "totalNSCLCClaims": 82,
    "volumeTier": "high",
    "email": "g.osei@nyp-oncology.example",
    "boardCertified": true
  },
  {
    "id": "phy_009",
    "npi": "1000000009",
    "firstName": "Emily",
    "lastName": "Carter",
    "specialty": "Medical Oncology",
    "affiliation": "UC Davis Comprehensive Cancer Center",
    "city": "Sacramento",
    "state": "CA",
    "icd10ClaimVolume": {"C341": 68, "C342": 27, "C343": 9},
    "totalNSCLCClaims": 104,
    "volumeTier": "high",
    "email": "e.carter@ucdavis.example",
    "boardCertified": true
  },
  {
    "id": "phy_010",
    "npi": "1000000010",
    "firstName": "Lucas",
    "lastName": "Moretti",
    "specialty": "Pulmonology",
    "affiliation": "Brigham and Women's Hospital",
    "city": "Boston",
    "state": "MA",
    "icd10ClaimVolume": {"C341": 39, "C342": 17},
    "totalNSCLCClaims": 56,
    "volumeTier": "high",
    "email": "l.moretti@bwh.example",
    "boardCertified": true
  },
  {
    "id": "phy_011",
    "npi": "1000000011",
    "firstName": "Samira",
    "lastName": "Khan",
    "specialty": "Medical Oncology",
    "affiliation": "Roswell Park Comprehensive Cancer Center",
    "city": "Buffalo",
    "state": "NY",
    "icd10ClaimVolume": {"C341": 74, "C342": 22, "C349": 10},
    "totalNSCLCClaims": 106,
    "volumeTier": "high",
    "email": "s.khan@roswellpark.example",
    "boardCertified": true
  },
  {
    "id": "phy_012",
    "npi": "1000000012",
    "firstName": "Thomas",
    "lastName": "Reed",
    "specialty": "Thoracic Surgery",
    "affiliation": "UPMC Hillman Cancer Center",
    "city": "Pittsburgh",
    "state": "PA",
    "icd10ClaimVolume": {"C341": 25, "C342": 9},
    "totalNSCLCClaims": 34,
    "volumeTier": "low",
    "email": "t.reed@upmc.example",
    "boardCertified": true
  },
  {
    "id": "phy_013",
    "npi": "1000000013",
    "firstName": "Hannah",
    "lastName": "Weiss",
    "specialty": "Medical Oncology",
    "affiliation": "University of Rochester Medical Center",
    "city": "Rochester",
    "state": "NY",
    "icd10ClaimVolume": {"C341": 58, "C342": 21, "C343": 4},
    "totalNSCLCClaims": 83,
    "volumeTier": "high",
    "email": "h.weiss@urmc.example",
    "boardCertified": true
  },
  {
    "id": "phy_014",
    "npi": "1000000014",
    "firstName": "Omar",
    "lastName": "Haddad",
    "specialty": "Pulmonology",
    "affiliation": "Yale New Haven Hospital",
    "city": "New Haven",
    "state": "CT",
    "icd10ClaimVolume": {"C341": 44, "C342": 19},
    "totalNSCLCClaims": 63,
    "volumeTier": "high",
    "email": "o.haddad@yale.example",
    "boardCertified": true
  },
  {
    "id": "phy_015",
    "npi": "1000000015",
    "firstName": "Sofia",
    "lastName": "Martinez",
    "specialty": "Medical Oncology",
    "affiliation": "MD Anderson Cancer Center",
    "city": "Houston",
    "state": "TX",
    "icd10ClaimVolume": {"C341": 130, "C342": 55, "C343": 24},
    "totalNSCLCClaims": 209,
    "volumeTier": "very_high",
    "email": "s.martinez@mdanderson.example",
    "boardCertified": true
  },
  {
    "id": "phy_016",
    "npi": "1000000016",
    "firstName": "Caleb",
    "lastName": "Brooks",
    "specialty": "Pulmonology",
    "affiliation": "Baylor St. Luke's Medical Center",
    "city": "Houston",
    "state": "TX",
    "icd10ClaimVolume": {"C341": 48, "C342": 23},
    "totalNSCLCClaims": 71,
    "volumeTier": "high",
    "email": "c.brooks@baylor.example",
    "boardCertified": true
  },
  {
    "id": "phy_017",
    "npi": "1000000017",
    "firstName": "Isabella",
    "lastName": "Garcia",
    "specialty": "Medical Oncology",
    "affiliation": "UC San Diego Moores Cancer Center",
    "city": "San Diego",
    "state": "CA",
    "icd10ClaimVolume": {"C341": 85, "C342": 34, "C349": 12},
    "totalNSCLCClaims": 131,
    "volumeTier": "very_high",
    "email": "i.garcia@ucsd.example",
    "boardCertified": true
  },
  {
    "id": "phy_018",
    "npi": "1000000018",
    "firstName": "Ethan",
    "lastName": "Nguyen",
    "specialty": "Radiation Oncology",
    "affiliation": "Moffitt Cancer Center",
    "city": "Tampa",
    "state": "FL",
    "icd10ClaimVolume": {"C341": 60, "C342": 20},
    "totalNSCLCClaims": 80,
    "volumeTier": "high",
    "email": "e.nguyen@moffitt.example",
    "boardCertified": true
  },
  {
    "id": "phy_019",
    "npi": "1000000019",
    "firstName": "Arjun",
    "lastName": "Mehta",
    "specialty": "Medical Oncology",
    "affiliation": "Northwestern Medicine",
    "city": "Chicago",
    "state": "IL",
    "icd10ClaimVolume": {"C341": 77, "C342": 29, "C343": 8},
    "totalNSCLCClaims": 114,
    "volumeTier": "high",
    "email": "a.mehta@northwestern.example",
    "boardCertified": true
  },
  {
    "id": "phy_020",
    "npi": "1000000020",
    "firstName": "Sarah",
    "lastName": "Johnson",
    "specialty": "Pulmonology",
    "affiliation": "University of Chicago Medicine",
    "city": "Chicago",
    "state": "IL",
    "icd10ClaimVolume": {"C341": 42, "C342": 15},
    "totalNSCLCClaims": 57,
    "volumeTier": "high",
    "email": "s.johnson@uchicago.example",
    "boardCertified": true
  },
  {
    "id": "phy_021",
    "npi": "1000000021",
    "firstName": "Lily",
    "lastName": "Park",
    "specialty": "Medical Oncology",
    "affiliation": "Fred Hutch Cancer Center",
    "city": "Seattle",
    "state": "WA",
    "icd10ClaimVolume": {"C341": 69, "C342": 24, "C349": 6},
    "totalNSCLCClaims": 99,
    "volumeTier": "high",
    "email": "l.park@fredhutch.example",
    "boardCertified": true
  },
  {
    "id": "phy_022",
    "npi": "1000000022",
    "firstName": "Benjamin",
    "lastName": "Lee",
    "specialty": "Thoracic Surgery",
    "affiliation": "Swedish Cancer Institute",
    "city": "Seattle",
    "state": "WA",
    "icd10ClaimVolume": {"C341": 31, "C342": 10},
    "totalNSCLCClaims": 41,
    "volumeTier": "low",
    "email": "b.lee@swedish.example",
    "boardCertified": true
  },
  {
    "id": "phy_023",
    "npi": "1000000023",
    "firstName": "Naomi",
    "lastName": "Williams",
    "specialty": "Medical Oncology",
    "affiliation": "Emory Winship Cancer Institute",
    "city": "Atlanta",
    "state": "GA",
    "icd10ClaimVolume": {"C341": 63, "C342": 18, "C343": 5},
    "totalNSCLCClaims": 86,
    "volumeTier": "high",
    "email": "n.williams@emory.example",
    "boardCertified": true
  },
  {
    "id": "phy_024",
    "npi": "1000000024",
    "firstName": "James",
    "lastName": "Wilson",
    "specialty": "Pulmonology",
    "affiliation": "Duke University Hospital",
    "city": "Durham",
    "state": "NC",
    "icd10ClaimVolume": {"C341": 55, "C342": 16},
    "totalNSCLCClaims": 71,
    "volumeTier": "high",
    "email": "j.wilson@duke.example",
    "boardCertified": true
  },
  {
    "id": "phy_025",
    "npi": "1000000025",
    "firstName": "Fatima",
    "lastName": "Al-Mansoori",
    "specialty": "Medical Oncology",
    "affiliation": "Mayo Clinic Phoenix",
    "city": "Phoenix",
    "state": "AZ",
    "icd10ClaimVolume": {"C341": 80, "C342": 30, "C343": 12},
    "totalNSCLCClaims": 122,
    "volumeTier": "very_high",
    "email": "f.almansoori@mayo.example",
    "boardCertified": true
  },
  {
    "id": "phy_026",
    "npi": "1000000026",
    "firstName": "Daniel",
    "lastName": "Murphy",
    "specialty": "Radiation Oncology",
    "affiliation": "UCHealth University of Colorado Hospital",
    "city": "Aurora",
    "state": "CO",
    "icd10ClaimVolume": {"C341": 47, "C342": 14},
    "totalNSCLCClaims": 61,
    "volumeTier": "high",
    "email": "d.murphy@uchealth.example",
    "boardCertified": true
  },
  {
    "id": "phy_027",
    "npi": "1000000027",
    "firstName": "Rachel",
    "lastName": "Miller",
    "specialty": "Medical Oncology",
    "affiliation": "Columbia University Irving Medical Center",
    "city": "New York",
    "state": "NY",
    "icd10ClaimVolume": {"C341": 73, "C342": 26, "C349": 9},
    "totalNSCLCClaims": 108,
    "volumeTier": "high",
    "email": "r.miller@cumc.example",
    "boardCertified": true
  },
  {
    "id": "phy_028",
    "npi": "1000000028",
    "firstName": "Kevin",
    "lastName": "Brown",
    "specialty": "Pulmonology",
    "affiliation": "University of Michigan Health",
    "city": "Ann Arbor",
    "state": "MI",
    "icd10ClaimVolume": {"C341": 38, "C342": 13},
    "totalNSCLCClaims": 51,
    "volumeTier": "high",
    "email": "k.brown@umich.example",
    "boardCertified": true
  },
  {
    "id": "phy_029",
    "npi": "1000000029",
    "firstName": "Anika",
    "lastName": "Rao",
    "specialty": "Medical Oncology",
    "affiliation": "Vanderbilt-Ingram Cancer Center",
    "city": "Nashville",
    "state": "TN",
    "icd10ClaimVolume": {"C341": 66, "C342": 18, "C343": 8},
    "totalNSCLCClaims": 92,
    "volumeTier": "high",
    "email": "a.rao@vumc.example",
    "boardCertified": true
  },
  {
    "id": "phy_030",
    "npi": "1000000030",
    "firstName": "Michael",
    "lastName": "Davis",
    "specialty": "Thoracic Surgery",
    "affiliation": "Siteman Cancer Center",
    "city": "St. Louis",
    "state": "MO",
    "icd10ClaimVolume": {"C341": 28, "C342": 7},
    "totalNSCLCClaims": 35,
    "volumeTier": "low",
    "email": "m.davis@siteman.example",
    "boardCertified": true
  },
  {
    "id": "phy_031",
    "npi": "1000000031",
    "firstName": "Claire",
    "lastName": "Thompson",
    "specialty": "Medical Oncology",
    "affiliation": "Mayo Clinic Rochester",
    "city": "Rochester",
    "state": "MN",
    "icd10ClaimVolume": {"C341": 91, "C342": 37, "C349": 14},
    "totalNSCLCClaims": 142,
    "volumeTier": "very_high",
    "email": "c.thompson@mayo.example",
    "boardCertified": true
  },
  {
    "id": "phy_032",
    "npi": "1000000032",
    "firstName": "Julian",
    "lastName": "Scott",
    "specialty": "Pulmonology",
    "affiliation": "OHSU Knight Cancer Institute",
    "city": "Portland",
    "state": "OR",
    "icd10ClaimVolume": {"C341": 36, "C342": 12},
    "totalNSCLCClaims": 48,
    "volumeTier": "low",
    "email": "j.scott@ohsu.example",
    "boardCertified": true
  },
  {
    "id": "phy_033",
    "npi": "1000000033",
    "firstName": "Leila",
    "lastName": "Ahmed",
    "specialty": "Medical Oncology",
    "affiliation": "UVA Health",
    "city": "Charlottesville",
    "state": "VA",
    "icd10ClaimVolume": {"C341": 59, "C342": 19, "C343": 7},
    "totalNSCLCClaims": 85,
    "volumeTier": "high",
    "email": "l.ahmed@uva.example",
    "boardCertified": true
  },
  {
    "id": "phy_034",
    "npi": "1000000034",
    "firstName": "Victor",
    "lastName": "Chen",
    "specialty": "Radiation Oncology",
    "affiliation": "Johns Hopkins Hospital",
    "city": "Baltimore",
    "state": "MD",
    "icd10ClaimVolume": {"C341": 71, "C342": 24, "C349": 11},
    "totalNSCLCClaims": 106,
    "volumeTier": "high",
    "email": "v.chen@hopkins.example",
    "boardCertified": true
  },
  {
    "id": "phy_035",
    "npi": "1000000035",
    "firstName": "Maria",
    "lastName": "Lopez",
    "specialty": "Pulmonology",
    "affiliation": "Renown Regional Medical Center",
    "city": "Reno",
    "state": "NV",
    "icd10ClaimVolume": {"C341": 34, "C342": 10},
    "totalNSCLCClaims": 44,
    "volumeTier": "low",
    "email": "m.lopez@renown.example",
    "boardCertified": true
  },
  {
    "id": "phy_036",
    "npi": "1000000036",
    "firstName": "Peter",
    "lastName": "Anderson",
    "specialty": "Medical Oncology",
    "affiliation": "Huntsman Cancer Institute",
    "city": "Salt Lake City",
    "state": "UT",
    "icd10ClaimVolume": {"C341": 76, "C342": 28, "C343": 9},
    "totalNSCLCClaims": 113,
    "volumeTier": "high",
    "email": "p.anderson@huntsman.example",
    "boardCertified": true
  }
]
